donatello_api/__init__.py
donatello_api/client.py
donatello_api/driver.py
donatello_api/exceptions.py
donatello_api/models.py
donatello_api-1.0.4.dist-info/LICENSE
donatello_api-1.0.4.dist-info/METADATA
donatello_api-1.0.4.dist-info/WHEEL
donatello_api-1.0.4.dist-info/top_level.txt
donatello_api-1.0.4.dist-info/RECORD
