Metadata-Version: 2.1
Name: donatello-api
Version: 1.0.4
Summary: 🐍 Python API wrapper for Ukrainian donate service Donatello
Home-page: https://github.com/selfkilla666/donatello_api
Download-URL: https://github.com/selfkilla666/donatello_api/blob/main/dist/donatello_api-1.0.4.tar.gz
Author: selfkilla666
Author-email: selfkilla666 <selfkilla666@yahoo.com>
License: MIT License (MIT)
Project-URL: Homepage, https://github.com/selfkilla666/donatello_api/
Classifier: Programming Language :: Python
Classifier: Programming Language :: Python :: 3
Classifier: Programming Language :: Python :: 3.7
Classifier: Programming Language :: Python :: 3.8
Classifier: Programming Language :: Python :: 3.9
Classifier: Programming Language :: Python :: 3.10
Classifier: Operating System :: OS Independent
Classifier: Topic :: Software Development :: Libraries
Classifier: Topic :: Software Development :: Libraries :: Python Modules
Classifier: Topic :: Utilities
Classifier: Typing :: Typed
Requires-Python: >=3.7.0
License-File: LICENSE
Requires-Dist: aiohttp
Requires-Dist: requests
Requires-Dist: pydantic
